{
  "cluster_label": 0,
  "cluster_classes": [
    {
      "candidate_id": "ClsC_17b175d2",
      "class_label": "Stainless Steel Families",
      "class_description": "Families of stainless steels categorized by their dominant metallurgical structure: austenitic, ferritic, and martensitic.",
      "class_type_hint": "MaterialFamily",
      "class_group": "Steel Metallurgy",
      "confidence": 0.95,
      "evidence_excerpt": "Austenitic, ferritic, and martensitic stainless steels are specific families within stainless steels.",
      "member_ids": [],
      "members": [],
      "remarks": []
    },
    {
      "candidate_id": "ClsC_297a52fd",
      "class_label": "Steel Metallurgical Structures",
      "class_description": "Metallurgical structures found in steels, including austenitic, ferritic, and martensitic.",
      "class_type_hint": "MetallurgicalStructure",
      "class_group": "Steel Metallurgy",
      "confidence": 0.9,
      "evidence_excerpt": "Austenitic, ferritic, and martensitic are metallurgical structures in steels.",
      "member_ids": [],
      "members": [],
      "remarks": []
    },
    {
      "candidate_id": "ClsR_aed0d686",
      "class_label": "Austenitic Structure",
      "class_description": "Metallurgical structure characterized by austenite, found in 300 Series stainless steels and nickel base alloys.",
      "class_type_hint": "MetallurgicalStructure",
      "class_group": "Steel Metallurgy",
      "confidence": 0.9,
      "evidence_excerpt": "Austenitic, ferritic, and martensitic are metallurgical structures in steels.",
      "member_ids": [
        "Can_2acbb9eb"
      ],
      "members": [
        {
          "id": "Can_2acbb9eb",
          "entity_name": "austenitic",
          "entity_description": "A type of metallurgical structure (austenite) found in 300 Series stainless steels and nickel base alloys, known for its corrosion resistance.",
          "entity_type_hint": "MetallurgicalStructure"
        }
      ],
      "remarks": []
    },
    {
      "candidate_id": "ClsR_ed9c5658",
      "class_label": "Ferritic Structure",
      "class_description": "Metallurgical structure characterized by ferrite, found in carbon and low alloy steels and many 400 series stainless steels.",
      "class_type_hint": "MetallurgicalStructure",
      "class_group": "Steel Metallurgy",
      "confidence": 0.9,
      "evidence_excerpt": "Austenitic, ferritic, and martensitic are metallurgical structures in steels.",
      "member_ids": [
        "Can_449bd7c2"
      ],
      "members": [
        {
          "id": "Can_449bd7c2",
          "entity_name": "ferritic",
          "entity_description": "A type of metallurgical structure (ferrite) found in carbon and low alloy steels and many 400 series stainless steels, known for its corrosion resistance.",
          "entity_type_hint": "MetallurgicalStructure"
        }
      ],
      "remarks": []
    },
    {
      "candidate_id": "ClsR_423fb320",
      "class_label": "Martensitic Structure",
      "class_description": "Metallurgical structure characterized by martensite, found in some stainless steels.",
      "class_type_hint": "MetallurgicalStructure",
      "class_group": "Steel Metallurgy",
      "confidence": 0.9,
      "evidence_excerpt": "Austenitic, ferritic, and martensitic are metallurgical structures in steels.",
      "member_ids": [
        "Can_c3c96b1a"
      ],
      "members": [
        {
          "id": "Can_c3c96b1a",
          "entity_name": "martensitic",
          "entity_description": "A metallurgical structure (martensite) found in some stainless steels, known for its corrosion resistance.",
          "entity_type_hint": "Material"
        }
      ],
      "remarks": []
    },
    {
      "candidate_id": "ClsR_8e6e239d",
      "class_label": "Austenitic Stainless Steels",
      "class_description": "Stainless steels with austenitic structure, including 300 Series types.",
      "class_type_hint": "MaterialFamily",
      "class_group": "Steel Metallurgy",
      "confidence": 0.95,
      "evidence_excerpt": "Austenitic, ferritic, and martensitic stainless steels are specific families within stainless steels.",
      "member_ids": [
        "En_d9cbe1b8"
      ],
      "members": [
        {
          "id": "En_d9cbe1b8",
          "entity_name": "austenitic stainless steels",
          "entity_description": "300 Series stainless steels including Types 304, 304L, 304H, 309, 310, 316, 316L, 316H, 321, 321H, 347, and 347H.",
          "entity_type_hint": "Material"
        }
      ],
      "remarks": []
    },
    {
      "candidate_id": "ClsR_0ca3c51c",
      "class_label": "Ferritic Stainless Steels",
      "class_description": "Stainless steels with ferritic structure, including Types 405, 409, 430, 442, and 446.",
      "class_type_hint": "MaterialFamily",
      "class_group": "Steel Metallurgy",
      "confidence": 0.95,
      "evidence_excerpt": "Austenitic, ferritic, and martensitic stainless steels are specific families within stainless steels.",
      "member_ids": [
        "En_31c964a4"
      ],
      "members": [
        {
          "id": "En_31c964a4",
          "entity_name": "ferritic stainless steels",
          "entity_description": "A family of stainless steels including Types 405, 409, 430, 442, and 446.",
          "entity_type_hint": "Material"
        }
      ],
      "remarks": []
    },
    {
      "candidate_id": "ClsR_4ad44c21",
      "class_label": "Martensitic Stainless Steels",
      "class_description": "Stainless steels with martensitic structure, including Types 410, 410S, 416, 420, 440A, 440B, and 440C.",
      "class_type_hint": "MaterialFamily",
      "class_group": "Steel Metallurgy",
      "confidence": 0.95,
      "evidence_excerpt": "Austenitic, ferritic, and martensitic stainless steels are specific families within stainless steels.",
      "member_ids": [
        "En_e3269efb"
      ],
      "members": [
        {
          "id": "En_e3269efb",
          "entity_name": "martensitic stainless steel",
          "entity_description": "A type of stainless steel that includes Types 410, 410S, 416, 420, 440A, 440B, and 440C.",
          "entity_type_hint": "Material"
        }
      ],
      "remarks": []
    }
  ],
  "llm_raw": "```json\n[\n  {\n    \"function\": \"split_class\",\n    \"args\": {\n      \"source_class_id\": \"ClsC_297a52fd\",\n      \"splits\": [\n        {\n          \"name\": \"Austenitic Structure\",\n          \"description\": \"Metallurgical structure characterized by austenite, found in 300 Series stainless steels and nickel base alloys.\",\n          \"class_type_hint\": \"MetallurgicalStructure\",\n          \"member_ids\": [\"Can_2acbb9eb\"],\n          \"provisional_id\": \"SPLIT_Austenitic_Structure\"\n        },\n        {\n          \"name\": \"Ferritic Structure\",\n          \"description\": \"Metallurgical structure characterized by ferrite, found in carbon and low alloy steels and many 400 series stainless steels.\",\n          \"class_type_hint\": \"MetallurgicalStructure\",\n          \"member_ids\": [\"Can_449bd7c2\"],\n          \"provisional_id\": \"SPLIT_Ferritic_Structure\"\n        },\n        {\n          \"name\": \"Martensitic Structure\",\n          \"description\": \"Metallurgical structure characterized by martensite, found in some stainless steels.\",\n          \"class_type_hint\": \"MetallurgicalStructure\",\n          \"member_ids\": [\"Can_c3c96b1a\"],\n          \"provisional_id\": \"SPLIT_Martensitic_Structure\"\n        }\n      ],\n      \"justification\": \"ClsC_297a52fd is overloaded, grouping distinct metallurgical structures (austenitic, ferritic, martensitic) that are already represented as separate classes; splitting clarifies schema and avoids redundancy.\",\n      \"remark\": null,\n      \"confidence\": 0.95\n    }\n  },\n  {\n    \"function\": \"merge_classes\",\n    \"args\": {\n      \"class_ids\": [\n        \"ClsR_aed0d686\",\n        \"SPLIT_Austenitic_Structure\"\n      ],\n      \"provisional_id\": \"MERGE_Austenitic_Structure\",\n      \"new_name\": \"Austenitic Structure\",\n      \"new_description\": \"Metallurgical structure characterized by austenite, found in 300 Series stainless steels and nickel base alloys.\",\n      \"new_class_type_hint\": \"MetallurgicalStructure\",\n      \"justification\": \"ClsR_aed0d686 and SPLIT_Austenitic_Structure are duplicates, both representing the austenitic metallurgical structure with identical entity membership and description.\",\n      \"remark\": null,\n      \"confidence\": 0.98\n    }\n  },\n  {\n    \"function\": \"merge_classes\",\n    \"args\": {\n      \"class_ids\": [\n        \"ClsR_ed9c5658\",\n        \"SPLIT_Ferritic_Structure\"\n      ],\n      \"provisional_id\": \"MERGE_Ferritic_Structure\",\n      \"new_name\": \"Ferritic Structure\",\n      \"new_description\": \"Metallurgical structure characterized by ferrite, found in carbon and low alloy steels and many 400 series stainless steels.\",\n      \"new_class_type_hint\": \"MetallurgicalStructure\",\n      \"justification\": \"ClsR_ed9c5658 and SPLIT_Ferritic_Structure are duplicates, both representing the ferritic metallurgical structure with identical entity membership and description.\",\n      \"remark\": null,\n      \"confidence\": 0.98\n    }\n  },\n  {\n    \"function\": \"merge_classes\",\n    \"args\": {\n      \"class_ids\": [\n        \"ClsR_423fb320\",\n        \"SPLIT_Martensitic_Structure\"\n      ],\n      \"provisional_id\": \"MERGE_Martensitic_Structure\",\n      \"new_name\": \"Martensitic Structure\",\n      \"new_description\": \"Metallurgical structure characterized by martensite, found in some stainless steels.\",\n      \"new_class_type_hint\": \"MetallurgicalStructure\",\n      \"justification\": \"ClsR_423fb320 and SPLIT_Martensitic_Structure are duplicates, both representing the martensitic metallurgical structure with identical entity membership and description.\",\n      \"remark\": null,\n      \"confidence\": 0.98\n    }\n  },\n  {\n    \"function\": \"modify_class\",\n    \"args\": {\n      \"class_id\": \"ClsC_17b175d2\",\n      \"new_name\": \"Stainless Steel Families\",\n      \"new_description\": \"Families of stainless steels categorized by their dominant metallurgical structure: austenitic, ferritic, and martensitic.\",\n      \"new_class_type_hint\": \"MaterialFamily\",\n      \"new_class_group\": \"Stainless Steel Classification\",\n      \"remark\": null,\n      \"justification\": \"ClsC_17b175d2 represents families of stainless steels, which is a broader classification than metallurgical structures; assigning a more precise Class_Group clarifies schema.\",\n      \"confidence\": 0.9\n    }\n  },\n  {\n    \"function\": \"modify_class\",\n    \"args\": {\n      \"class_id\": \"ClsR_8e6e239d\",\n      \"new_name\": \"Austenitic Stainless Steels\",\n      \"new_description\": \"Stainless steels with austenitic structure, including 300 Series types.\",\n      \"new_class_type_hint\": \"MaterialFamily\",\n      \"new_class_group\": \"Stainless Steel Classification\",\n      \"remark\": null,\n      \"justification\": \"ClsR_8e6e239d is a family of stainless steels defined by austenitic structure; grouping under 'Stainless Steel Classification' aligns with its domain.\",\n      \"confidence\": 0.9\n    }\n  },\n  {\n    \"function\": \"modify_class\",\n    \"args\": {\n      \"class_id\": \"ClsR_0ca3c51c\",\n      \"new_name\": \"Ferritic Stainless Steels\",\n      \"new_description\": \"Stainless steels with ferritic structure, including Types 405, 409, 430, 442, and 446.\",\n      \"new_class_type_hint\": \"MaterialFamily\",\n      \"new_class_group\": \"Stainless Steel Classification\",\n      \"remark\": null,\n      \"justification\": \"ClsR_0ca3c51c is a family of stainless steels defined by ferritic structure; grouping under 'Stainless Steel Classification' aligns with its domain.\",\n      \"confidence\": 0.9\n    }\n  },\n  {\n    \"function\": \"modify_class\",\n    \"args\": {\n      \"class_id\": \"ClsR_4ad44c21\",\n      \"new_name\": \"Martensitic Stainless Steels\",\n      \"new_description\": \"Stainless steels with martensitic structure, including Types 410, 410S, 416, 420, 440A, 440B, and 440C.\",\n      \"new_class_type_hint\": \"MaterialFamily\",\n      \"new_class_group\": \"Stainless Steel Classification\",\n      \"remark\": null,\n      \"justification\": \"ClsR_4ad44c21 is a family of stainless steels defined by martensitic structure; grouping under 'Stainless Steel Classification' aligns with its domain.\",\n      \"confidence\": 0.9\n    }\n  }\n]\n```",
  "parsed_steps": [
    {
      "function": "split_class",
      "args": {
        "source_class_id": "ClsC_297a52fd",
        "splits": [
          {
            "name": "Austenitic Structure",
            "description": "Metallurgical structure characterized by austenite, found in 300 Series stainless steels and nickel base alloys.",
            "class_type_hint": "MetallurgicalStructure",
            "member_ids": [
              "Can_2acbb9eb"
            ],
            "provisional_id": "SPLIT_Austenitic_Structure"
          },
          {
            "name": "Ferritic Structure",
            "description": "Metallurgical structure characterized by ferrite, found in carbon and low alloy steels and many 400 series stainless steels.",
            "class_type_hint": "MetallurgicalStructure",
            "member_ids": [
              "Can_449bd7c2"
            ],
            "provisional_id": "SPLIT_Ferritic_Structure"
          },
          {
            "name": "Martensitic Structure",
            "description": "Metallurgical structure characterized by martensite, found in some stainless steels.",
            "class_type_hint": "MetallurgicalStructure",
            "member_ids": [
              "Can_c3c96b1a"
            ],
            "provisional_id": "SPLIT_Martensitic_Structure"
          }
        ],
        "justification": "ClsC_297a52fd is overloaded, grouping distinct metallurgical structures (austenitic, ferritic, martensitic) that are already represented as separate classes; splitting clarifies schema and avoids redundancy.",
        "remark": null,
        "confidence": 0.95
      }
    },
    {
      "function": "merge_classes",
      "args": {
        "class_ids": [
          "ClsR_aed0d686",
          "SPLIT_Austenitic_Structure"
        ],
        "provisional_id": "MERGE_Austenitic_Structure",
        "new_name": "Austenitic Structure",
        "new_description": "Metallurgical structure characterized by austenite, found in 300 Series stainless steels and nickel base alloys.",
        "new_class_type_hint": "MetallurgicalStructure",
        "justification": "ClsR_aed0d686 and SPLIT_Austenitic_Structure are duplicates, both representing the austenitic metallurgical structure with identical entity membership and description.",
        "remark": null,
        "confidence": 0.98
      }
    },
    {
      "function": "merge_classes",
      "args": {
        "class_ids": [
          "ClsR_ed9c5658",
          "SPLIT_Ferritic_Structure"
        ],
        "provisional_id": "MERGE_Ferritic_Structure",
        "new_name": "Ferritic Structure",
        "new_description": "Metallurgical structure characterized by ferrite, found in carbon and low alloy steels and many 400 series stainless steels.",
        "new_class_type_hint": "MetallurgicalStructure",
        "justification": "ClsR_ed9c5658 and SPLIT_Ferritic_Structure are duplicates, both representing the ferritic metallurgical structure with identical entity membership and description.",
        "remark": null,
        "confidence": 0.98
      }
    },
    {
      "function": "merge_classes",
      "args": {
        "class_ids": [
          "ClsR_423fb320",
          "SPLIT_Martensitic_Structure"
        ],
        "provisional_id": "MERGE_Martensitic_Structure",
        "new_name": "Martensitic Structure",
        "new_description": "Metallurgical structure characterized by martensite, found in some stainless steels.",
        "new_class_type_hint": "MetallurgicalStructure",
        "justification": "ClsR_423fb320 and SPLIT_Martensitic_Structure are duplicates, both representing the martensitic metallurgical structure with identical entity membership and description.",
        "remark": null,
        "confidence": 0.98
      }
    },
    {
      "function": "modify_class",
      "args": {
        "class_id": "ClsC_17b175d2",
        "new_name": "Stainless Steel Families",
        "new_description": "Families of stainless steels categorized by their dominant metallurgical structure: austenitic, ferritic, and martensitic.",
        "new_class_type_hint": "MaterialFamily",
        "new_class_group": "Stainless Steel Classification",
        "remark": null,
        "justification": "ClsC_17b175d2 represents families of stainless steels, which is a broader classification than metallurgical structures; assigning a more precise Class_Group clarifies schema.",
        "confidence": 0.9
      }
    },
    {
      "function": "modify_class",
      "args": {
        "class_id": "ClsR_8e6e239d",
        "new_name": "Austenitic Stainless Steels",
        "new_description": "Stainless steels with austenitic structure, including 300 Series types.",
        "new_class_type_hint": "MaterialFamily",
        "new_class_group": "Stainless Steel Classification",
        "remark": null,
        "justification": "ClsR_8e6e239d is a family of stainless steels defined by austenitic structure; grouping under 'Stainless Steel Classification' aligns with its domain.",
        "confidence": 0.9
      }
    },
    {
      "function": "modify_class",
      "args": {
        "class_id": "ClsR_0ca3c51c",
        "new_name": "Ferritic Stainless Steels",
        "new_description": "Stainless steels with ferritic structure, including Types 405, 409, 430, 442, and 446.",
        "new_class_type_hint": "MaterialFamily",
        "new_class_group": "Stainless Steel Classification",
        "remark": null,
        "justification": "ClsR_0ca3c51c is a family of stainless steels defined by ferritic structure; grouping under 'Stainless Steel Classification' aligns with its domain.",
        "confidence": 0.9
      }
    },
    {
      "function": "modify_class",
      "args": {
        "class_id": "ClsR_4ad44c21",
        "new_name": "Martensitic Stainless Steels",
        "new_description": "Stainless steels with martensitic structure, including Types 410, 410S, 416, 420, 440A, 440B, and 440C.",
        "new_class_type_hint": "MaterialFamily",
        "new_class_group": "Stainless Steel Classification",
        "remark": null,
        "justification": "ClsR_4ad44c21 is a family of stainless steels defined by martensitic structure; grouping under 'Stainless Steel Classification' aligns with its domain.",
        "confidence": 0.9
      }
    }
  ],
  "executed_decisions": [
    {
      "action": "split_class",
      "source_class_id": "ClsC_297a52fd",
      "source_class_id_resolved": "ClsC_297a52fd",
      "created_classes": [],
      "justification": "ClsC_297a52fd is overloaded, grouping distinct metallurgical structures (austenitic, ferritic, martensitic) that are already represented as separate classes; splitting clarifies schema and avoids redundancy.",
      "remark": null,
      "confidence": 0.95
    },
    {
      "action": "merge_skip_too_few",
      "requested_class_ids": [
        "ClsR_aed0d686",
        "SPLIT_Austenitic_Structure"
      ],
      "valid_class_ids": [
        "ClsR_aed0d686"
      ],
      "justification": "ClsR_aed0d686 and SPLIT_Austenitic_Structure are duplicates, both representing the austenitic metallurgical structure with identical entity membership and description.",
      "remark": null,
      "confidence": 0.98
    },
    {
      "action": "merge_skip_too_few",
      "requested_class_ids": [
        "ClsR_ed9c5658",
        "SPLIT_Ferritic_Structure"
      ],
      "valid_class_ids": [
        "ClsR_ed9c5658"
      ],
      "justification": "ClsR_ed9c5658 and SPLIT_Ferritic_Structure are duplicates, both representing the ferritic metallurgical structure with identical entity membership and description.",
      "remark": null,
      "confidence": 0.98
    },
    {
      "action": "merge_skip_too_few",
      "requested_class_ids": [
        "ClsR_423fb320",
        "SPLIT_Martensitic_Structure"
      ],
      "valid_class_ids": [
        "ClsR_423fb320"
      ],
      "justification": "ClsR_423fb320 and SPLIT_Martensitic_Structure are duplicates, both representing the martensitic metallurgical structure with identical entity membership and description.",
      "remark": null,
      "confidence": 0.98
    },
    {
      "action": "modify_class",
      "class_id": "ClsC_17b175d2",
      "class_id_resolved": "ClsC_17b175d2",
      "new_name": "Stainless Steel Families",
      "new_description": "Families of stainless steels categorized by their dominant metallurgical structure: austenitic, ferritic, and martensitic.",
      "new_class_type_hint": "MaterialFamily",
      "new_class_group": "Stainless Steel Classification",
      "remark": null,
      "justification": "ClsC_17b175d2 represents families of stainless steels, which is a broader classification than metallurgical structures; assigning a more precise Class_Group clarifies schema.",
      "confidence": 0.9
    },
    {
      "action": "modify_class",
      "class_id": "ClsR_8e6e239d",
      "class_id_resolved": "ClsR_8e6e239d",
      "new_name": "Austenitic Stainless Steels",
      "new_description": "Stainless steels with austenitic structure, including 300 Series types.",
      "new_class_type_hint": "MaterialFamily",
      "new_class_group": "Stainless Steel Classification",
      "remark": null,
      "justification": "ClsR_8e6e239d is a family of stainless steels defined by austenitic structure; grouping under 'Stainless Steel Classification' aligns with its domain.",
      "confidence": 0.9
    },
    {
      "action": "modify_class",
      "class_id": "ClsR_0ca3c51c",
      "class_id_resolved": "ClsR_0ca3c51c",
      "new_name": "Ferritic Stainless Steels",
      "new_description": "Stainless steels with ferritic structure, including Types 405, 409, 430, 442, and 446.",
      "new_class_type_hint": "MaterialFamily",
      "new_class_group": "Stainless Steel Classification",
      "remark": null,
      "justification": "ClsR_0ca3c51c is a family of stainless steels defined by ferritic structure; grouping under 'Stainless Steel Classification' aligns with its domain.",
      "confidence": 0.9
    },
    {
      "action": "modify_class",
      "class_id": "ClsR_4ad44c21",
      "class_id_resolved": "ClsR_4ad44c21",
      "new_name": "Martensitic Stainless Steels",
      "new_description": "Stainless steels with martensitic structure, including Types 410, 410S, 416, 420, 440A, 440B, and 440C.",
      "new_class_type_hint": "MaterialFamily",
      "new_class_group": "Stainless Steel Classification",
      "remark": null,
      "justification": "ClsR_4ad44c21 is a family of stainless steels defined by martensitic structure; grouping under 'Stainless Steel Classification' aligns with its domain.",
      "confidence": 0.9
    }
  ],
  "provisional_to_real": {},
  "timestamp": "2025-12-28T00:23:16Z"
}